<?xml version="1.0" encoding="UTF-8" ?>
<!DOCTYPE ViewObject SYSTEM "jbo_03_01.dtd">
<!---->
<ViewObject
  xmlns="http://xmlns.oracle.com/bc4j"
  Name="ProjectsVO"
  Version="12.1.3.2.1"
  InheritPersonalization="merge"
  BindingStyle="OracleName"
  CustomQuery="false"
  PageIterMode="Full"
  SelectListFlags="1"
  FromListFlags="1"
  WhereFlags="1"
  SelectAllAttributes="false">
  <ViewAccessor
    Name="UsersDropDownVO1"
    ViewObjectName="oracle.adf.research.model.bc.dropdownlists.UsersDropDownVO"
    RowLevelBinds="true"/>
  <ViewAccessor
    Name="CategoryVO1"
    ViewObjectName="oracle.adf.research.model.bc.dropdownlists.CategoryVO"
    RowLevelBinds="true"/>
  <ViewAccessor
    Name="TypeDropDownVO1"
    ViewObjectName="oracle.adf.research.model.bc.dropdownlists.TypeDropDownVO"
    RowLevelBinds="true"/>
  <ListBinding
    Name="LOV_UserId"
    ListVOName="UsersDropDownVO1"
    ListRangeSize="-1"
    NullValueFlag="none"
    MRUCount="0">
    <AttrArray Name="AttrNames">
      <Item Value="UserId"/>
    </AttrArray>
    <AttrArray Name="AttrExpressions"/>
    <AttrArray Name="ListAttrNames">
      <Item Value="UserId"/>
    </AttrArray>
    <AttrArray Name="ListDisplayAttrNames">
      <Item Value="FirstName"/>
      <Item Value="LastName"/>
    </AttrArray>
    <DisplayCriteria/>
  </ListBinding>
  <ListBinding
    Name="LOV_CategoryId"
    ListVOName="CategoryVO1"
    ListRangeSize="-1"
    NullValueFlag="none"
    MRUCount="0">
    <AttrArray Name="AttrNames">
      <Item Value="CategoryId"/>
    </AttrArray>
    <AttrArray Name="AttrExpressions"/>
    <AttrArray Name="ListAttrNames">
      <Item Value="CategoryId"/>
    </AttrArray>
    <AttrArray Name="ListDisplayAttrNames">
      <Item Value="CategoryName"/>
    </AttrArray>
    <DisplayCriteria/>
  </ListBinding>
  <ListBinding
    Name="LOV_Type"
    ListVOName="TypeDropDownVO1"
    ListRangeSize="-1"
    NullValueFlag="none"
    MRUCount="0">
    <AttrArray Name="AttrNames">
      <Item Value="Type"/>
    </AttrArray>
    <AttrArray Name="AttrExpressions"/>
    <AttrArray Name="ListAttrNames">
      <Item Value="ID"/>
    </AttrArray>
    <AttrArray Name="ListDisplayAttrNames">
      <Item Value="TYPE"/>
    </AttrArray>
    <DisplayCriteria/>
  </ListBinding>
  <EntityUsage
    Name="ProjectsEO"
    Entity="oracle.adf.research.model.bc.entity.ProjectsEO"/>
  <ViewAttribute
    Name="ProjectId"
    IsNotNull="true"
    PrecisionRule="true"
    EntityAttrName="ProjectId"
    EntityUsage="ProjectsEO"
    AliasName="PROJECT_ID"/>
  <ViewAttribute
    Name="ProjectName"
    IsNotNull="true"
    PrecisionRule="true"
    EntityAttrName="ProjectName"
    EntityUsage="ProjectsEO"
    AliasName="PROJECT_NAME"/>
  <ViewAttribute
    Name="Description"
    IsNotNull="true"
    PrecisionRule="true"
    EntityAttrName="Description"
    EntityUsage="ProjectsEO"
    AliasName="DESCRIPTION"/>
  <ViewAttribute
    Name="Link"
    IsNotNull="true"
    PrecisionRule="true"
    EntityAttrName="Link"
    EntityUsage="ProjectsEO"
    AliasName="LINK"/>
  <ViewAttribute
    Name="CategoryId"
    IsNotNull="true"
    PrecisionRule="true"
    EntityAttrName="CategoryId"
    EntityUsage="ProjectsEO"
    AliasName="CATEGORY_ID"
    LOVName="LOV_CategoryId">
    <Properties>
      <SchemaBasedProperties>
        <CONTROLTYPE
          Value="choice"/>
      </SchemaBasedProperties>
    </Properties>
  </ViewAttribute>
  <ViewAttribute
    Name="ProjectFile"
    IsQueriable="false"
    PrecisionRule="true"
    EntityAttrName="ProjectFile"
    EntityUsage="ProjectsEO"
    AliasName="PROJECT_FILE"/>
  <ViewAttribute
    Name="UserId"
    IsNotNull="true"
    PrecisionRule="true"
    EntityAttrName="UserId"
    EntityUsage="ProjectsEO"
    AliasName="USER_ID"
    LOVName="LOV_UserId">
    <Properties>
      <SchemaBasedProperties>
        <CONTROLTYPE
          Value="choice"/>
      </SchemaBasedProperties>
    </Properties>
  </ViewAttribute>
  <ViewAttribute
    Name="ProjectDate"
    PrecisionRule="true"
    EntityAttrName="ProjectDate"
    EntityUsage="ProjectsEO"
    AliasName="PROJECT_DATE"/>
  <ViewAttribute
    Name="ProjectImage"
    IsQueriable="false"
    PrecisionRule="true"
    EntityAttrName="ProjectImage"
    EntityUsage="ProjectsEO"
    AliasName="PROJECT_IMAGE"/>
  <ViewAttribute
    Name="Screenshot1"
    IsQueriable="false"
    PrecisionRule="true"
    EntityAttrName="Screenshot1"
    EntityUsage="ProjectsEO"
    AliasName="SCREENSHOT1"/>
  <ViewAttribute
    Name="Screenshot2"
    IsQueriable="false"
    PrecisionRule="true"
    EntityAttrName="Screenshot2"
    EntityUsage="ProjectsEO"
    AliasName="SCREENSHOT2"/>
  <ViewAttribute
    Name="Path"
    PrecisionRule="true"
    EntityAttrName="Path"
    EntityUsage="ProjectsEO"
    AliasName="PATH"/>
  <ViewAttribute
    Name="Code"
    PrecisionRule="true"
    EntityAttrName="Code"
    EntityUsage="ProjectsEO"
    AliasName="CODE"/>
  <ViewAttribute
    Name="Type"
    PrecisionRule="true"
    EntityAttrName="Type"
    EntityUsage="ProjectsEO"
    AliasName="TYPE"
    LOVName="LOV_Type">
    <Properties>
      <SchemaBasedProperties>
        <CONTROLTYPE
          Value="radio"/>
      </SchemaBasedProperties>
    </Properties>
  </ViewAttribute>
  <ViewCriteria
    Name="PublicProjrctsCriteria"
    ViewObjectName="oracle.adf.research.model.bc.uiview.ProjectsVO"
    Conjunction="AND">
    <Properties>
      <CustomProperties>
        <Property
          Name="displayOperators"
          Value="InAdvancedMode"/>
        <Property
          Name="autoExecute"
          Value="false"/>
        <Property
          Name="allowConjunctionOverride"
          Value="true"/>
        <Property
          Name="showInList"
          Value="true"/>
        <Property
          Name="mode"
          Value="Basic"/>
      </CustomProperties>
    </Properties>
    <ViewCriteriaRow
      Name="ProjectsVOCriteria_row_0"
      UpperColumns="1">
      <ViewCriteriaItem
        Name="Type"
        ViewAttribute="Type"
        Operator="="
        Conjunction="AND"
        Value="Public"
        Required="Optional"/>
    </ViewCriteriaRow>
  </ViewCriteria>
  <ViewCriteria
    Name="PrivateProjectsCriteria"
    ViewObjectName="oracle.adf.research.model.bc.uiview.ProjectsVO"
    Conjunction="AND">
    <Properties>
      <CustomProperties>
        <Property
          Name="displayOperators"
          Value="InAdvancedMode"/>
        <Property
          Name="autoExecute"
          Value="false"/>
        <Property
          Name="allowConjunctionOverride"
          Value="true"/>
        <Property
          Name="showInList"
          Value="true"/>
        <Property
          Name="mode"
          Value="Basic"/>
      </CustomProperties>
    </Properties>
    <ViewCriteriaRow
      Name="ProjectsVOCriteria_row_0"
      UpperColumns="1">
      <ViewCriteriaItem
        Name="Type"
        ViewAttribute="Type"
        Operator="="
        Conjunction="AND"
        Value="Private"
        Required="Optional"/>
    </ViewCriteriaRow>
  </ViewCriteria>
  <ViewLinkAccessor
    Name="Category"
    ViewLink="oracle.adf.research.model.bc.vulink.CategoryProjectsVuLink"
    Type="oracle.jbo.Row"
    Reversed="true"
    IsUpdateable="false"/>
  <ViewLinkAccessor
    Name="Users"
    ViewLink="oracle.adf.research.model.bc.vulink.UserProjectsVuLink"
    Type="oracle.jbo.Row"
    Reversed="true"
    IsUpdateable="false"/>
  <ResourceBundle>
    <PropertiesBundle
      PropertiesFile="oracle.adf.research.model.ModelBundle"/>
  </ResourceBundle>
</ViewObject>
